LICENSE
punch_api/__init__.py
punch_api/dag.py
punch_api/datasets.py
punch_api/logger.py
punch_api/metrics/__init__.py
punch_api/metrics/counter.py
punch_api/metrics/gauge.py
punch_api/metrics/histogram.py
punch_api/metrics/metric_context.py
punch_api/nodes.py
punch_api-8.1.13.dist-info/LICENSE
punch_api-8.1.13.dist-info/WHEEL
punch_api-8.1.13.dist-info/METADATA
punch_api-8.1.13.dist-info/RECORD
