Metadata-Version: 2.1
Name: punch-api
Version: 8.1.13
Summary: Punch Python and PySpark Public API
Home-page: https://punchplatform.com
Author: Punch
Author-email: contact@punchplatform.com
Maintainer: Punch
Maintainer-email: contact@punchplatform.com
Requires-Python: >=3.10.4,<4.0.0
Classifier: Programming Language :: Python :: 3
Requires-Dist: prometheus-client (>=0.12.0,<0.13.0)
Project-URL: Documentation, https://doc.punchplatform.com
Project-URL: Repository, https://github.com/punchplatform
